{
  "metadata": {
    "pipeline_type": "global",
    "model_name": "LOF",
    "feature_set": "Bivariate",
    "iteration_id": 4,
    "run_timestamp_utc": "2025-10-04T05:48:04.090741"
  },
  "tuning_results": {
    "best_hyperparameters": {
      "n_neighbors": 10
    },
    "validation_best_threshold": 513.7584838867188,
    "best_threshold": 1.2767530573738948,
    "validation_cost": 100.0,
    "calibration_cost": 34.01389489184428,
    "total_tuning_time_seconds": 3999.3420315384865
  },
  "reporting_metrics_aggregated": {
    "mean_training_time_seconds": 2.3316255458788615,
    "mean_prediction_time_seconds": 2.49292536320697,
    "DR": 1.0,
    "FAR": 0.6315120711562897,
    "MTTD_minutes": 1.9999999999999996
  },
  "reporting_metrics_per_stream": [
    {
      "detected": true,
      "mttd_minutes": 0.0,
      "false_alarms": "133",
      "total_negatives": "133",
      "stream_path": "data/incident_files/smoothed/incident_20.csv",
      "train_time_seconds": 2.3316255458788615,
      "predict_time_seconds": 2.4410366660449654
    },
    {
      "detected": true,
      "mttd_minutes": 0.0,
      "false_alarms": "139",
      "total_negatives": "139",
      "stream_path": "data/incident_files/smoothed/incident_53.csv",
      "train_time_seconds": 2.3316255458788615,
      "predict_time_seconds": 2.495648470008746
    },
    {
      "detected": true,
      "mttd_minutes": 20.0,
      "false_alarms": "57",
      "total_negatives": "133",
      "stream_path": "data/incident_files/smoothed/incident_68.csv",
      "train_time_seconds": 2.3316255458788615,
      "predict_time_seconds": 2.4642720320262015
    },
    {
      "detected": true,
      "mttd_minutes": 0.0,
      "false_alarms": "135",
      "total_negatives": "135",
      "stream_path": "data/incident_files/smoothed/incident_80.csv",
      "train_time_seconds": 2.3316255458788615,
      "predict_time_seconds": 2.4742246329551563
    },
    {
      "detected": true,
      "mttd_minutes": 0.0,
      "false_alarms": "34",
      "total_negatives": "132",
      "stream_path": "data/incident_files/smoothed/incident_95.csv",
      "train_time_seconds": 2.3316255458788615,
      "predict_time_seconds": 2.476640690001659
    },
    {
      "detected": true,
      "mttd_minutes": 10.0,
      "false_alarms": "34",
      "total_negatives": "130",
      "stream_path": "data/incident_files/smoothed/incident_96.csv",
      "train_time_seconds": 2.3316255458788615,
      "predict_time_seconds": 2.446276233997196
    },
    {
      "detected": true,
      "mttd_minutes": 0.0,
      "false_alarms": "139",
      "total_negatives": "139",
      "stream_path": "data/incident_files/smoothed/incident_106.csv",
      "train_time_seconds": 2.3316255458788615,
      "predict_time_seconds": 2.494472582009621
    },
    {
      "detected": true,
      "mttd_minutes": 0.0,
      "false_alarms": "133",
      "total_negatives": "133",
      "stream_path": "data/incident_files/smoothed/incident_116.csv",
      "train_time_seconds": 2.3316255458788615,
      "predict_time_seconds": 2.51871705299709
    },
    {
      "detected": true,
      "mttd_minutes": 0.0,
      "false_alarms": "139",
      "total_negatives": "139",
      "stream_path": "data/incident_files/smoothed/incident_117.csv",
      "train_time_seconds": 2.3316255458788615,
      "predict_time_seconds": 2.4446301070274785
    },
    {
      "detected": true,
      "mttd_minutes": 0.0,
      "false_alarms": "138",
      "total_negatives": "138",
      "stream_path": "data/incident_files/smoothed/incident_131.csv",
      "train_time_seconds": 2.3316255458788615,
      "predict_time_seconds": 2.5305804269155487
    },
    {
      "detected": true,
      "mttd_minutes": 0.0,
      "false_alarms": "130",
      "total_negatives": "130",
      "stream_path": "data/incident_files/smoothed/incident_132.csv",
      "train_time_seconds": 2.3316255458788615,
      "predict_time_seconds": 2.5355732650496066
    },
    {
      "detected": true,
      "mttd_minutes": 0.0,
      "false_alarms": "20",
      "total_negatives": "127",
      "stream_path": "data/incident_files/smoothed/incident_133.csv",
      "train_time_seconds": 2.3316255458788615,
      "predict_time_seconds": 2.4835549470735714
    },
    {
      "detected": true,
      "mttd_minutes": 10.0,
      "false_alarms": "15",
      "total_negatives": "132",
      "stream_path": "data/incident_files/smoothed/incident_142.csv",
      "train_time_seconds": 2.3316255458788615,
      "predict_time_seconds": 2.477094782050699
    },
    {
      "detected": true,
      "mttd_minutes": 5.0,
      "false_alarms": "28",
      "total_negatives": "139",
      "stream_path": "data/incident_files/smoothed/incident_145.csv",
      "train_time_seconds": 2.3316255458788615,
      "predict_time_seconds": 2.483019491075538
    },
    {
      "detected": true,
      "mttd_minutes": 10.0,
      "false_alarms": "14",
      "total_negatives": "132",
      "stream_path": "data/incident_files/smoothed/incident_153.csv",
      "train_time_seconds": 2.3316255458788615,
      "predict_time_seconds": 2.5036078239791095
    },
    {
      "detected": true,
      "mttd_minutes": 10.0,
      "false_alarms": "10",
      "total_negatives": "140",
      "stream_path": "data/incident_files/smoothed/incident_159.csv",
      "train_time_seconds": 2.3316255458788615,
      "predict_time_seconds": 2.486643795040436
    },
    {
      "detected": true,
      "mttd_minutes": 0.0,
      "false_alarms": "133",
      "total_negatives": "133",
      "stream_path": "data/incident_files/smoothed/incident_171.csv",
      "train_time_seconds": 2.3316255458788615,
      "predict_time_seconds": 2.4593173939501867
    },
    {
      "detected": true,
      "mttd_minutes": 0.0,
      "false_alarms": "134",
      "total_negatives": "134",
      "stream_path": "data/incident_files/smoothed/incident_172.csv",
      "train_time_seconds": 2.3316255458788615,
      "predict_time_seconds": 2.483878997969441
    },
    {
      "detected": true,
      "mttd_minutes": 0.0,
      "false_alarms": "135",
      "total_negatives": "135",
      "stream_path": "data/incident_files/smoothed/incident_177.csv",
      "train_time_seconds": 2.3316255458788615,
      "predict_time_seconds": 2.464364969986491
    },
    {
      "detected": true,
      "mttd_minutes": 0.0,
      "false_alarms": "18",
      "total_negatives": "138",
      "stream_path": "data/incident_files/smoothed/incident_181.csv",
      "train_time_seconds": 2.3316255458788615,
      "predict_time_seconds": 2.4924226209986955
    },
    {
      "detected": true,
      "mttd_minutes": 0.0,
      "false_alarms": "134",
      "total_negatives": "134",
      "stream_path": "data/incident_files/smoothed/incident_184.csv",
      "train_time_seconds": 2.3316255458788615,
      "predict_time_seconds": 2.49087334505748
    },
    {
      "detected": true,
      "mttd_minutes": 0.0,
      "false_alarms": "31",
      "total_negatives": "137",
      "stream_path": "data/incident_files/smoothed/incident_187.csv",
      "train_time_seconds": 2.3316255458788615,
      "predict_time_seconds": 2.493389782961458
    },
    {
      "detected": true,
      "mttd_minutes": 0.0,
      "false_alarms": "135",
      "total_negatives": "135",
      "stream_path": "data/incident_files/smoothed/incident_218.csv",
      "train_time_seconds": 2.3316255458788615,
      "predict_time_seconds": 2.513581622042693
    },
    {
      "detected": true,
      "mttd_minutes": 0.0,
      "false_alarms": "133",
      "total_negatives": "133",
      "stream_path": "data/incident_files/smoothed/incident_219.csv",
      "train_time_seconds": 2.3316255458788615,
      "predict_time_seconds": 2.4737653370248154
    },
    {
      "detected": true,
      "mttd_minutes": 0.0,
      "false_alarms": "138",
      "total_negatives": "138",
      "stream_path": "data/incident_files/smoothed/incident_222.csv",
      "train_time_seconds": 2.3316255458788615,
      "predict_time_seconds": 2.467491849907674
    },
    {
      "detected": true,
      "mttd_minutes": 0.0,
      "false_alarms": "47",
      "total_negatives": "137",
      "stream_path": "data/incident_files/smoothed/incident_240.csv",
      "train_time_seconds": 2.3316255458788615,
      "predict_time_seconds": 2.5057973290095106
    },
    {
      "detected": true,
      "mttd_minutes": 0.0,
      "false_alarms": "4",
      "total_negatives": "137",
      "stream_path": "data/incident_files/smoothed/incident_242.csv",
      "train_time_seconds": 2.3316255458788615,
      "predict_time_seconds": 2.517376652918756
    },
    {
      "detected": true,
      "mttd_minutes": 0.0,
      "false_alarms": "44",
      "total_negatives": "137",
      "stream_path": "data/incident_files/smoothed/incident_245.csv",
      "train_time_seconds": 2.3316255458788615,
      "predict_time_seconds": 2.493931979057379
    },
    {
      "detected": true,
      "mttd_minutes": 5.0,
      "false_alarms": "9",
      "total_negatives": "126",
      "stream_path": "data/incident_files/smoothed/incident_264.csv",
      "train_time_seconds": 2.3316255458788615,
      "predict_time_seconds": 2.529542167088948
    },
    {
      "detected": true,
      "mttd_minutes": 0.0,
      "false_alarms": "139",
      "total_negatives": "139",
      "stream_path": "data/incident_files/smoothed/incident_289.csv",
      "train_time_seconds": 2.3316255458788615,
      "predict_time_seconds": 2.521372818038799
    },
    {
      "detected": true,
      "mttd_minutes": 0.0,
      "false_alarms": "13",
      "total_negatives": "139",
      "stream_path": "data/incident_files/smoothed/incident_323.csv",
      "train_time_seconds": 2.3316255458788615,
      "predict_time_seconds": 2.53775036893785
    },
    {
      "detected": true,
      "mttd_minutes": 0.0,
      "false_alarms": "133",
      "total_negatives": "133",
      "stream_path": "data/incident_files/smoothed/incident_340.csv",
      "train_time_seconds": 2.3316255458788615,
      "predict_time_seconds": 2.4928226970368996
    },
    {
      "detected": true,
      "mttd_minutes": 0.0,
      "false_alarms": "30",
      "total_negatives": "132",
      "stream_path": "data/incident_files/smoothed/incident_360.csv",
      "train_time_seconds": 2.3316255458788615,
      "predict_time_seconds": 2.530297342920676
    },
    {
      "detected": true,
      "mttd_minutes": 0.0,
      "false_alarms": "139",
      "total_negatives": "139",
      "stream_path": "data/incident_files/smoothed/incident_429.csv",
      "train_time_seconds": 2.3316255458788615,
      "predict_time_seconds": 2.5229790190933272
    },
    {
      "detected": true,
      "mttd_minutes": 0.0,
      "false_alarms": "135",
      "total_negatives": "135",
      "stream_path": "data/incident_files/smoothed/incident_448.csv",
      "train_time_seconds": 2.3316255458788615,
      "predict_time_seconds": 2.5054384199902415
    }
  ],
  "timing_extras": {
    "global_training_time_seconds": 326.4275764230406,
    "calibration_scoring_time_seconds": 351.75632027804386,
    "total_reporting_predict_time_seconds": 87.25238771224394
  }
}