{
  "metadata": {
    "pipeline_type": "global",
    "model_name": "LSTM",
    "feature_set": "Speed",
    "iteration_id": 1,
    "run_timestamp_utc": "2025-09-26T23:37:56.829779"
  },
  "tuning_results": {
    "best_hyperparameters": {
      "batch_size": 32,
      "lstm_units": 16,
      "n_layers": 1,
      "random_state": 42,
      "window_size": 48
    },
    "validation_best_threshold": 0.011864942684769572,
    "best_threshold": 0.007719178070699926,
    "validation_cost": 3.9145929544673868,
    "calibration_cost": 5.82657538743249,
    "total_tuning_time_seconds": 96546.48460843007
  },
  "reporting_metrics_aggregated": {
    "mean_training_time_seconds": 28.020488322192875,
    "mean_prediction_time_seconds": 0.9774252786282367,
    "DR": 0.9714285714285714,
    "FAR": 0.02507970244420829,
    "MTTD_minutes": 0.29411764705882354
  },
  "reporting_metrics_per_stream": [
    {
      "detected": true,
      "mttd_minutes": 0.0,
      "false_alarms": "2",
      "total_negatives": "137",
      "stream_path": "data/incident_files/smoothed/incident_56.csv",
      "train_time_seconds": 28.020488322192875,
      "predict_time_seconds": 0.9566282130035688
    },
    {
      "detected": true,
      "mttd_minutes": 0.0,
      "false_alarms": "4",
      "total_negatives": "134",
      "stream_path": "data/incident_files/smoothed/incident_78.csv",
      "train_time_seconds": 28.020488322192875,
      "predict_time_seconds": 1.1777148800028954
    },
    {
      "detected": true,
      "mttd_minutes": 0.0,
      "false_alarms": "17",
      "total_negatives": "136",
      "stream_path": "data/incident_files/smoothed/incident_88.csv",
      "train_time_seconds": 28.020488322192875,
      "predict_time_seconds": 1.0184985059968312
    },
    {
      "detected": true,
      "mttd_minutes": 0.0,
      "false_alarms": "3",
      "total_negatives": "138",
      "stream_path": "data/incident_files/smoothed/incident_90.csv",
      "train_time_seconds": 28.020488322192875,
      "predict_time_seconds": 0.950555629999144
    },
    {
      "detected": true,
      "mttd_minutes": 0.0,
      "false_alarms": "4",
      "total_negatives": "137",
      "stream_path": "data/incident_files/smoothed/incident_91.csv",
      "train_time_seconds": 28.020488322192875,
      "predict_time_seconds": 0.9536903259941027
    },
    {
      "detected": true,
      "mttd_minutes": 0.0,
      "false_alarms": "3",
      "total_negatives": "138",
      "stream_path": "data/incident_files/smoothed/incident_102.csv",
      "train_time_seconds": 28.020488322192875,
      "predict_time_seconds": 1.0270338519985671
    },
    {
      "detected": false,
      "mttd_minutes": null,
      "false_alarms": "0",
      "total_negatives": "134",
      "stream_path": "data/incident_files/smoothed/incident_109.csv",
      "train_time_seconds": 28.020488322192875,
      "predict_time_seconds": 0.9601074009988224
    },
    {
      "detected": true,
      "mttd_minutes": 0.0,
      "false_alarms": "2",
      "total_negatives": "136",
      "stream_path": "data/incident_files/smoothed/incident_123.csv",
      "train_time_seconds": 28.020488322192875,
      "predict_time_seconds": 0.9311519390030298
    },
    {
      "detected": true,
      "mttd_minutes": 0.0,
      "false_alarms": "2",
      "total_negatives": "133",
      "stream_path": "data/incident_files/smoothed/incident_155.csv",
      "train_time_seconds": 28.020488322192875,
      "predict_time_seconds": 0.9458057709998684
    },
    {
      "detected": true,
      "mttd_minutes": 0.0,
      "false_alarms": "4",
      "total_negatives": "137",
      "stream_path": "data/incident_files/smoothed/incident_173.csv",
      "train_time_seconds": 28.020488322192875,
      "predict_time_seconds": 1.017645084997639
    },
    {
      "detected": true,
      "mttd_minutes": 0.0,
      "false_alarms": "9",
      "total_negatives": "140",
      "stream_path": "data/incident_files/smoothed/incident_185.csv",
      "train_time_seconds": 28.020488322192875,
      "predict_time_seconds": 0.9064500930035138
    },
    {
      "detected": true,
      "mttd_minutes": 5.0,
      "false_alarms": "1",
      "total_negatives": "131",
      "stream_path": "data/incident_files/smoothed/incident_188.csv",
      "train_time_seconds": 28.020488322192875,
      "predict_time_seconds": 0.8819684710033471
    },
    {
      "detected": true,
      "mttd_minutes": 0.0,
      "false_alarms": "1",
      "total_negatives": "132",
      "stream_path": "data/incident_files/smoothed/incident_216.csv",
      "train_time_seconds": 28.020488322192875,
      "predict_time_seconds": 0.9284629600006156
    },
    {
      "detected": true,
      "mttd_minutes": 0.0,
      "false_alarms": "4",
      "total_negatives": "132",
      "stream_path": "data/incident_files/smoothed/incident_224.csv",
      "train_time_seconds": 28.020488322192875,
      "predict_time_seconds": 1.1313147000037134
    },
    {
      "detected": true,
      "mttd_minutes": 0.0,
      "false_alarms": "2",
      "total_negatives": "130",
      "stream_path": "data/incident_files/smoothed/incident_231.csv",
      "train_time_seconds": 28.020488322192875,
      "predict_time_seconds": 0.994044123995991
    },
    {
      "detected": true,
      "mttd_minutes": 0.0,
      "false_alarms": "7",
      "total_negatives": "135",
      "stream_path": "data/incident_files/smoothed/incident_251.csv",
      "train_time_seconds": 28.020488322192875,
      "predict_time_seconds": 0.960517207000521
    },
    {
      "detected": true,
      "mttd_minutes": 0.0,
      "false_alarms": "5",
      "total_negatives": "130",
      "stream_path": "data/incident_files/smoothed/incident_255.csv",
      "train_time_seconds": 28.020488322192875,
      "predict_time_seconds": 0.9721199319974403
    },
    {
      "detected": true,
      "mttd_minutes": 0.0,
      "false_alarms": "2",
      "total_negatives": "136",
      "stream_path": "data/incident_files/smoothed/incident_259.csv",
      "train_time_seconds": 28.020488322192875,
      "predict_time_seconds": 0.9299162649986101
    },
    {
      "detected": true,
      "mttd_minutes": 0.0,
      "false_alarms": "2",
      "total_negatives": "140",
      "stream_path": "data/incident_files/smoothed/incident_262.csv",
      "train_time_seconds": 28.020488322192875,
      "predict_time_seconds": 0.8790387889966951
    },
    {
      "detected": true,
      "mttd_minutes": 0.0,
      "false_alarms": "1",
      "total_negatives": "131",
      "stream_path": "data/incident_files/smoothed/incident_265.csv",
      "train_time_seconds": 28.020488322192875,
      "predict_time_seconds": 0.8963249579974217
    },
    {
      "detected": true,
      "mttd_minutes": 0.0,
      "false_alarms": "21",
      "total_negatives": "121",
      "stream_path": "data/incident_files/smoothed/incident_309.csv",
      "train_time_seconds": 28.020488322192875,
      "predict_time_seconds": 0.9134156989966868
    },
    {
      "detected": true,
      "mttd_minutes": 0.0,
      "false_alarms": "2",
      "total_negatives": "132",
      "stream_path": "data/incident_files/smoothed/incident_317.csv",
      "train_time_seconds": 28.020488322192875,
      "predict_time_seconds": 0.9017481599948951
    },
    {
      "detected": true,
      "mttd_minutes": 0.0,
      "false_alarms": "4",
      "total_negatives": "136",
      "stream_path": "data/incident_files/smoothed/incident_326.csv",
      "train_time_seconds": 28.020488322192875,
      "predict_time_seconds": 0.9313679500046419
    },
    {
      "detected": true,
      "mttd_minutes": 0.0,
      "false_alarms": "0",
      "total_negatives": "130",
      "stream_path": "data/incident_files/smoothed/incident_356.csv",
      "train_time_seconds": 28.020488322192875,
      "predict_time_seconds": 0.9981383729973459
    },
    {
      "detected": true,
      "mttd_minutes": 0.0,
      "false_alarms": "1",
      "total_negatives": "136",
      "stream_path": "data/incident_files/smoothed/incident_357.csv",
      "train_time_seconds": 28.020488322192875,
      "predict_time_seconds": 1.2795682859941735
    },
    {
      "detected": true,
      "mttd_minutes": 0.0,
      "false_alarms": "2",
      "total_negatives": "138",
      "stream_path": "data/incident_files/smoothed/incident_371.csv",
      "train_time_seconds": 28.020488322192875,
      "predict_time_seconds": 0.9391806540006655
    },
    {
      "detected": true,
      "mttd_minutes": 0.0,
      "false_alarms": "0",
      "total_negatives": "139",
      "stream_path": "data/incident_files/smoothed/incident_387.csv",
      "train_time_seconds": 28.020488322192875,
      "predict_time_seconds": 0.9204736230021808
    },
    {
      "detected": true,
      "mttd_minutes": 0.0,
      "false_alarms": "6",
      "total_negatives": "135",
      "stream_path": "data/incident_files/smoothed/incident_393.csv",
      "train_time_seconds": 28.020488322192875,
      "predict_time_seconds": 1.0650867919976008
    },
    {
      "detected": true,
      "mttd_minutes": 0.0,
      "false_alarms": "2",
      "total_negatives": "137",
      "stream_path": "data/incident_files/smoothed/incident_403.csv",
      "train_time_seconds": 28.020488322192875,
      "predict_time_seconds": 0.9813682359963423
    },
    {
      "detected": true,
      "mttd_minutes": 0.0,
      "false_alarms": "1",
      "total_negatives": "137",
      "stream_path": "data/incident_files/smoothed/incident_405.csv",
      "train_time_seconds": 28.020488322192875,
      "predict_time_seconds": 0.8946159390034154
    },
    {
      "detected": true,
      "mttd_minutes": 0.0,
      "false_alarms": "0",
      "total_negatives": "127",
      "stream_path": "data/incident_files/smoothed/incident_414.csv",
      "train_time_seconds": 28.020488322192875,
      "predict_time_seconds": 0.8910227009982918
    },
    {
      "detected": true,
      "mttd_minutes": 0.0,
      "false_alarms": "1",
      "total_negatives": "131",
      "stream_path": "data/incident_files/smoothed/incident_416.csv",
      "train_time_seconds": 28.020488322192875,
      "predict_time_seconds": 0.9863703120063292
    },
    {
      "detected": true,
      "mttd_minutes": 0.0,
      "false_alarms": "1",
      "total_negatives": "139",
      "stream_path": "data/incident_files/smoothed/incident_440.csv",
      "train_time_seconds": 28.020488322192875,
      "predict_time_seconds": 0.9320822160007083
    },
    {
      "detected": true,
      "mttd_minutes": 0.0,
      "false_alarms": "1",
      "total_negatives": "131",
      "stream_path": "data/incident_files/smoothed/incident_441.csv",
      "train_time_seconds": 28.020488322192875,
      "predict_time_seconds": 1.1295485510054277
    },
    {
      "detected": true,
      "mttd_minutes": 5.0,
      "false_alarms": "1",
      "total_negatives": "139",
      "stream_path": "data/incident_files/smoothed/incident_442.csv",
      "train_time_seconds": 28.020488322192875,
      "predict_time_seconds": 1.0269081579972408
    }
  ],
  "timing_extras": {
    "global_training_time_seconds": 3922.8683651070023,
    "calibration_scoring_time_seconds": 138.4543508929928,
    "total_reporting_predict_time_seconds": 34.209884751988284
  }
}