{
  "metadata": {
    "pipeline_type": "global",
    "model_name": "OneClassSVM",
    "feature_set": "Speed",
    "iteration_id": 5,
    "run_timestamp_utc": "2025-10-05T15:17:59.345228"
  },
  "tuning_results": {
    "best_hyperparameters": {
      "gamma": "scale",
      "kernel": "rbf",
      "nu": 0.1
    },
    "validation_best_threshold": 87.94346145869686,
    "best_threshold": 0.03314720341384446,
    "validation_cost": 25.78911201038406,
    "calibration_cost": 24.26462606691833,
    "total_tuning_time_seconds": 57070.389426897054
  },
  "reporting_metrics_aggregated": {
    "mean_training_time_seconds": 22.30322966796427,
    "mean_prediction_time_seconds": 8.32453373728557,
    "DR": 0.9714285714285714,
    "FAR": 0.36344314558979807,
    "MTTD_minutes": 5.4411764705882355
  },
  "reporting_metrics_per_stream": [
    {
      "detected": true,
      "mttd_minutes": 0.0,
      "false_alarms": "18",
      "total_negatives": "137",
      "stream_path": "data/incident_files/smoothed/incident_13.csv",
      "train_time_seconds": 22.30322966796427,
      "predict_time_seconds": 7.019502258001012
    },
    {
      "detected": true,
      "mttd_minutes": 0.0,
      "false_alarms": "96",
      "total_negatives": "134",
      "stream_path": "data/incident_files/smoothed/incident_14.csv",
      "train_time_seconds": 22.30322966796427,
      "predict_time_seconds": 6.938921591005055
    },
    {
      "detected": true,
      "mttd_minutes": 5.0,
      "false_alarms": "21",
      "total_negatives": "137",
      "stream_path": "data/incident_files/smoothed/incident_50.csv",
      "train_time_seconds": 22.30322966796427,
      "predict_time_seconds": 6.938911694000126
    },
    {
      "detected": true,
      "mttd_minutes": 25.0,
      "false_alarms": "0",
      "total_negatives": "134",
      "stream_path": "data/incident_files/smoothed/incident_54.csv",
      "train_time_seconds": 22.30322966796427,
      "predict_time_seconds": 6.977093638997758
    },
    {
      "detected": true,
      "mttd_minutes": 5.0,
      "false_alarms": "8",
      "total_negatives": "135",
      "stream_path": "data/incident_files/smoothed/incident_60.csv",
      "train_time_seconds": 22.30322966796427,
      "predict_time_seconds": 7.024960851995274
    },
    {
      "detected": true,
      "mttd_minutes": 10.0,
      "false_alarms": "12",
      "total_negatives": "131",
      "stream_path": "data/incident_files/smoothed/incident_63.csv",
      "train_time_seconds": 22.30322966796427,
      "predict_time_seconds": 8.272099283996795
    },
    {
      "detected": true,
      "mttd_minutes": 0.0,
      "false_alarms": "96",
      "total_negatives": "135",
      "stream_path": "data/incident_files/smoothed/incident_74.csv",
      "train_time_seconds": 22.30322966796427,
      "predict_time_seconds": 8.672144550000667
    },
    {
      "detected": true,
      "mttd_minutes": 15.0,
      "false_alarms": "15",
      "total_negatives": "125",
      "stream_path": "data/incident_files/smoothed/incident_84.csv",
      "train_time_seconds": 22.30322966796427,
      "predict_time_seconds": 7.7126008109989925
    },
    {
      "detected": true,
      "mttd_minutes": 0.0,
      "false_alarms": "58",
      "total_negatives": "133",
      "stream_path": "data/incident_files/smoothed/incident_94.csv",
      "train_time_seconds": 22.30322966796427,
      "predict_time_seconds": 9.663722208999388
    },
    {
      "detected": true,
      "mttd_minutes": 15.0,
      "false_alarms": "9",
      "total_negatives": "140",
      "stream_path": "data/incident_files/smoothed/incident_100.csv",
      "train_time_seconds": 22.30322966796427,
      "predict_time_seconds": 9.142724950004776
    },
    {
      "detected": true,
      "mttd_minutes": 5.0,
      "false_alarms": "30",
      "total_negatives": "138",
      "stream_path": "data/incident_files/smoothed/incident_113.csv",
      "train_time_seconds": 22.30322966796427,
      "predict_time_seconds": 9.536042150000867
    },
    {
      "detected": true,
      "mttd_minutes": 0.0,
      "false_alarms": "101",
      "total_negatives": "138",
      "stream_path": "data/incident_files/smoothed/incident_138.csv",
      "train_time_seconds": 22.30322966796427,
      "predict_time_seconds": 8.72370826099359
    },
    {
      "detected": true,
      "mttd_minutes": 5.0,
      "false_alarms": "11",
      "total_negatives": "135",
      "stream_path": "data/incident_files/smoothed/incident_161.csv",
      "train_time_seconds": 22.30322966796427,
      "predict_time_seconds": 8.525101844999881
    },
    {
      "detected": true,
      "mttd_minutes": 0.0,
      "false_alarms": "130",
      "total_negatives": "134",
      "stream_path": "data/incident_files/smoothed/incident_162.csv",
      "train_time_seconds": 22.30322966796427,
      "predict_time_seconds": 9.156850763996772
    },
    {
      "detected": true,
      "mttd_minutes": 0.0,
      "false_alarms": "73",
      "total_negatives": "137",
      "stream_path": "data/incident_files/smoothed/incident_166.csv",
      "train_time_seconds": 22.30322966796427,
      "predict_time_seconds": 9.495207533997018
    },
    {
      "detected": true,
      "mttd_minutes": 0.0,
      "false_alarms": "81",
      "total_negatives": "134",
      "stream_path": "data/incident_files/smoothed/incident_176.csv",
      "train_time_seconds": 22.30322966796427,
      "predict_time_seconds": 8.825864077000006
    },
    {
      "detected": true,
      "mttd_minutes": 0.0,
      "false_alarms": "106",
      "total_negatives": "130",
      "stream_path": "data/incident_files/smoothed/incident_180.csv",
      "train_time_seconds": 22.30322966796427,
      "predict_time_seconds": 8.404263863994856
    },
    {
      "detected": true,
      "mttd_minutes": 15.0,
      "false_alarms": "3",
      "total_negatives": "135",
      "stream_path": "data/incident_files/smoothed/incident_193.csv",
      "train_time_seconds": 22.30322966796427,
      "predict_time_seconds": 8.197875612000644
    },
    {
      "detected": true,
      "mttd_minutes": 0.0,
      "false_alarms": "135",
      "total_negatives": "135",
      "stream_path": "data/incident_files/smoothed/incident_199.csv",
      "train_time_seconds": 22.30322966796427,
      "predict_time_seconds": 7.64087022899912
    },
    {
      "detected": true,
      "mttd_minutes": 0.0,
      "false_alarms": "87",
      "total_negatives": "126",
      "stream_path": "data/incident_files/smoothed/incident_201.csv",
      "train_time_seconds": 22.30322966796427,
      "predict_time_seconds": 7.492218573999708
    },
    {
      "detected": true,
      "mttd_minutes": 0.0,
      "false_alarms": "14",
      "total_negatives": "131",
      "stream_path": "data/incident_files/smoothed/incident_205.csv",
      "train_time_seconds": 22.30322966796427,
      "predict_time_seconds": 8.124271769003826
    },
    {
      "detected": true,
      "mttd_minutes": 0.0,
      "false_alarms": "90",
      "total_negatives": "140",
      "stream_path": "data/incident_files/smoothed/incident_221.csv",
      "train_time_seconds": 22.30322966796427,
      "predict_time_seconds": 8.155846064000798
    },
    {
      "detected": true,
      "mttd_minutes": 5.0,
      "false_alarms": "24",
      "total_negatives": "127",
      "stream_path": "data/incident_files/smoothed/incident_227.csv",
      "train_time_seconds": 22.30322966796427,
      "predict_time_seconds": 7.424795737999375
    },
    {
      "detected": true,
      "mttd_minutes": 15.0,
      "false_alarms": "8",
      "total_negatives": "138",
      "stream_path": "data/incident_files/smoothed/incident_233.csv",
      "train_time_seconds": 22.30322966796427,
      "predict_time_seconds": 7.761097176997282
    },
    {
      "detected": true,
      "mttd_minutes": 0.0,
      "false_alarms": "12",
      "total_negatives": "138",
      "stream_path": "data/incident_files/smoothed/incident_267.csv",
      "train_time_seconds": 22.30322966796427,
      "predict_time_seconds": 7.873908149005729
    },
    {
      "detected": true,
      "mttd_minutes": 0.0,
      "false_alarms": "116",
      "total_negatives": "141",
      "stream_path": "data/incident_files/smoothed/incident_274.csv",
      "train_time_seconds": 22.30322966796427,
      "predict_time_seconds": 9.226458760000241
    },
    {
      "detected": true,
      "mttd_minutes": 5.0,
      "false_alarms": "8",
      "total_negatives": "141",
      "stream_path": "data/incident_files/smoothed/incident_284.csv",
      "train_time_seconds": 22.30322966796427,
      "predict_time_seconds": 8.491876457999751
    },
    {
      "detected": true,
      "mttd_minutes": 0.0,
      "false_alarms": "90",
      "total_negatives": "134",
      "stream_path": "data/incident_files/smoothed/incident_306.csv",
      "train_time_seconds": 22.30322966796427,
      "predict_time_seconds": 8.172496669998509
    },
    {
      "detected": true,
      "mttd_minutes": 15.0,
      "false_alarms": "14",
      "total_negatives": "132",
      "stream_path": "data/incident_files/smoothed/incident_341.csv",
      "train_time_seconds": 22.30322966796427,
      "predict_time_seconds": 9.269184930002666
    },
    {
      "detected": false,
      "mttd_minutes": null,
      "false_alarms": "4",
      "total_negatives": "138",
      "stream_path": "data/incident_files/smoothed/incident_344.csv",
      "train_time_seconds": 22.30322966796427,
      "predict_time_seconds": 11.838256041999557
    },
    {
      "detected": true,
      "mttd_minutes": 20.0,
      "false_alarms": "6",
      "total_negatives": "129",
      "stream_path": "data/incident_files/smoothed/incident_345.csv",
      "train_time_seconds": 22.30322966796427,
      "predict_time_seconds": 8.767556536004122
    },
    {
      "detected": true,
      "mttd_minutes": 15.0,
      "false_alarms": "7",
      "total_negatives": "132",
      "stream_path": "data/incident_files/smoothed/incident_347.csv",
      "train_time_seconds": 22.30322966796427,
      "predict_time_seconds": 7.574013452001964
    },
    {
      "detected": true,
      "mttd_minutes": 10.0,
      "false_alarms": "12",
      "total_negatives": "133",
      "stream_path": "data/incident_files/smoothed/incident_383.csv",
      "train_time_seconds": 22.30322966796427,
      "predict_time_seconds": 7.406071320001502
    },
    {
      "detected": true,
      "mttd_minutes": 0.0,
      "false_alarms": "130",
      "total_negatives": "130",
      "stream_path": "data/incident_files/smoothed/incident_398.csv",
      "train_time_seconds": 22.30322966796427,
      "predict_time_seconds": 7.558209939998051
    },
    {
      "detected": true,
      "mttd_minutes": 0.0,
      "false_alarms": "85",
      "total_negatives": "138",
      "stream_path": "data/incident_files/smoothed/incident_435.csv",
      "train_time_seconds": 22.30322966796427,
      "predict_time_seconds": 9.35395305199927
    }
  ],
  "timing_extras": {
    "global_training_time_seconds": 3122.452153514998,
    "calibration_scoring_time_seconds": 1004.5674985470105,
    "total_reporting_predict_time_seconds": 291.35868080499495
  }
}